LICENSE
README.rst
pyproject.toml
setup.py
sulekha_holtwinters_python/__init__.py
sulekha_holtwinters_python/data
sulekha_holtwinters_python/holtwinters.py
sulekha_holtwinters_python.egg-info/PKG-INFO
sulekha_holtwinters_python.egg-info/SOURCES.txt
sulekha_holtwinters_python.egg-info/dependency_links.txt
sulekha_holtwinters_python.egg-info/requires.txt
sulekha_holtwinters_python.egg-info/top_level.txt