Metadata-Version: 2.1
Name: sulekha-holtwinters-python
Version: 1.5.0
Summary: A Holt Winters implementation Python project using Pandas Dataframe
Home-page: https://github.com/sulekhaaloorravi/sulekha_holtwinters_python
Author: Sulekha Aloorravi
Author-email: Sulekha Aloorravi <sulekha.aloorravi@gmail.com>
Project-URL: Homepage, https://github.com/sulekhaaloorravi/sulekha_holtwinters_python
Keywords: Holt Winters Forecasting Experiment
Classifier: Programming Language :: Python :: 3
Classifier: License :: OSI Approved :: MIT License
Classifier: Operating System :: OS Independent
Requires-Python: >=3.8
License-File: LICENSE
